setup.py
pyfarm/__init__.py
pyfarm.jobtypes.egg-info/PKG-INFO
pyfarm.jobtypes.egg-info/SOURCES.txt
pyfarm.jobtypes.egg-info/dependency_links.txt
pyfarm.jobtypes.egg-info/namespace_packages.txt
pyfarm.jobtypes.egg-info/requires.txt
pyfarm.jobtypes.egg-info/top_level.txt
pyfarm/jobtypes/__init__.py
pyfarm/jobtypes/core.py