Metadata-Version: 1.1
Name: pyfarm.jobtypes
Version: 0.7.0-dev0
Summary: Sub-library which contains the code necessary to
Home-page: https://github.com/pyfarm/pyfarm-jobtypes
Author: Oliver Palmer
Author-email: development@pyfarm.net
License: Apache v2.0
Platform: UNKNOWN
Classifier: Development Status :: 2 - Pre-Alpha
Classifier: Environment :: Other Environment
Classifier: Intended Audience :: Developers
Classifier: License :: OSI Approved :: Apache Software License
Classifier: Natural Language :: English
Classifier: Operating System :: OS Independent
Classifier: Programming Language :: Python :: 2 :: Only
Classifier: Programming Language :: Python :: 2.5
Classifier: Programming Language :: Python :: 2.6
Classifier: Programming Language :: Python :: 2.7
Classifier: Topic :: System :: Distributed Computing
